attn_gan_pytorch/ConfigManagement.py
attn_gan_pytorch/CustomLayers.py
attn_gan_pytorch/Losses.py
attn_gan_pytorch/Networks.py
attn_gan_pytorch/Utils.py
attn_gan_pytorch/__init__.py
attn_gan_pytorch-0.3.dist-info/DESCRIPTION.rst
attn_gan_pytorch-0.3.dist-info/METADATA
attn_gan_pytorch-0.3.dist-info/RECORD
attn_gan_pytorch-0.3.dist-info/WHEEL
attn_gan_pytorch-0.3.dist-info/metadata.json
attn_gan_pytorch-0.3.dist-info/top_level.txt
